setup.py
cegads/ECUK.py
cegads/__init__.py
cegads/exceptions.py
cegads/model_data.py
cegads/appliances/__init__.py
cegads/appliances/appliance.py
cegads/appliances/factory.py
cegads/appliances/model.py
cegads/data/ECUK Table 3.10.csv
cegads/data/daily profiles.csv
cegads/data/number_of_appliances.csv
cegads/data/number_of_households.csv
cegads/households/__init__.py
cegads/households/household.py
cegads/scenarios/__init__.py
cegads/scenarios/factory.py
cegads/scenarios/scenario.py
cegads_domestic_model.egg-info/PKG-INFO
cegads_domestic_model.egg-info/SOURCES.txt
cegads_domestic_model.egg-info/dependency_links.txt
cegads_domestic_model.egg-info/top_level.txt