Metadata-Version: 1.0
Name: cegads-domestic-model
Version: 0.5
Summary: An energy consumption model for domestic appliances
Home-page: https://github.com/IESD/cegads-domestic-model
Author: Graeme Stuart
Author-email: gstuart@dmu.ac.uk
License: UNKNOWN
Platform: UNKNOWN
